piprepo/__init__.py
piprepo/command.py
piprepo/exceptions.py
piprepo/models.py
piprepo/utils.py
piprepo-0.1.3.dist-info/LICENSE
piprepo-0.1.3.dist-info/METADATA
piprepo-0.1.3.dist-info/WHEEL
piprepo-0.1.3.dist-info/entry_points.txt
piprepo-0.1.3.dist-info/top_level.txt
piprepo-0.1.3.dist-info/RECORD
